[{"_path":"/blog/jugendbundesliga-sued","_dir":"blog","_draft":false,"_partial":false,"_locale":"","title":"Jugendbundesliga Süd 2019/20 (Karlsruher SF 1)","description":"Herausforderung gegen den Titelverteidiger: Biberacher Jugend zeigt Kampfgeist trotz Niederlage in der Jugendbundesliga Süd.","date":"2019-10-12T00:00:00.000Z","badge":"Jugend","authors":"Jens Hoffmann","_type":"markdown","_id":"content:blog:20191012.jugendbundesliga-sued.md","_source":"content","_file":"blog/20191012.jugendbundesliga-sued.md","_extension":"md"},{"_path":"/impressum","_dir":"","_draft":false,"_partial":false,"_locale":"","title":"Impressum","description":"Kontaktdaten und rechtliche Informationen des Webseitenbetreibers.","container":true,"_type":"markdown","_id":"content:impressum.md","_source":"content","_file":"impressum.md","_extension":"md"}]