[{"_path":"/articles/design-tokens","_dir":"articles","_draft":false,"_partial":false,"_locale":"","title":"Customize Alpine","description":"Leverage the tokens.config.ts to give your identity to Alpine.","cover":"/articles/design-tokens.webp","date":"2022-08-23T00:00:00.000Z","layout":"article","_type":"markdown","_id":"content:articles:4.design-tokens.md","_source":"content","_file":"articles/4.design-tokens.md","_extension":"md"},{"_path":"/impressum","_dir":"","_draft":false,"_partial":false,"_locale":"","title":"Impressum","description":"Kontaktdaten und rechtliche Informationen des Webseitenbetreibers.","container":true,"_type":"markdown","_id":"content:impressum.md","_source":"content","_file":"impressum.md","_extension":"md"}]